VBCableSoundPlayer/VBCableSoundPlayer.py
VBCableSoundPlayer/__init__.py
vbcablesoundplayer-0.1.1.dist-info/LICENSE
vbcablesoundplayer-0.1.1.dist-info/METADATA
vbcablesoundplayer-0.1.1.dist-info/WHEEL
vbcablesoundplayer-0.1.1.dist-info/top_level.txt
vbcablesoundplayer-0.1.1.dist-info/RECORD
