Metadata-Version: 2.2
Name: VBCableSoundPlayer
Version: 0.1.1
Summary: This package outputs audio to the VBCable virtual audio device.
Author-email: nnnnnnn0090 <nnnnnnn0090@gmail.com>
License: MIT
Project-URL: Homepage, https://github.com/nnnnnnn0090/VBCableSoundPlayer
Classifier: Programming Language :: Python :: 3
Classifier: License :: OSI Approved :: MIT License
Classifier: Operating System :: OS Independent
Requires-Python: >=3.6
License-File: LICENSE
Requires-Dist: sounddevice
